casbin_sqlalchemy_adapter/__init__.py
casbin_sqlalchemy_adapter/adapter.py
casbin_sqlalchemy_adapter-1.4.0.dist-info/LICENSE
casbin_sqlalchemy_adapter-1.4.0.dist-info/METADATA
casbin_sqlalchemy_adapter-1.4.0.dist-info/WHEEL
casbin_sqlalchemy_adapter-1.4.0.dist-info/top_level.txt
casbin_sqlalchemy_adapter-1.4.0.dist-info/RECORD
