Metadata-Version: 2.1
Name: casbin_sqlalchemy_adapter
Version: 1.4.0
Summary: SQLAlchemy Adapter for PyCasbin
Home-page: https://github.com/pycasbin/sqlalchemy-adapter
Author: TechLee
Author-email: techlee@qq.com
License: Apache 2.0
Keywords: casbin,SQLAlchemy,casbin-adapter,rbac,access control,abac,acl,permission
Classifier: Programming Language :: Python :: 3.9
Classifier: Programming Language :: Python :: 3.10
Classifier: Programming Language :: Python :: 3.11
Classifier: Programming Language :: Python :: 3.12
Classifier: License :: OSI Approved :: Apache Software License
Classifier: Operating System :: OS Independent
Requires-Python: >=3.3
License-File: LICENSE
Requires-Dist: casbin>=0.8.1
Requires-Dist: SQLAlchemy>=1.2.18
